ClassWidgets/__init__.py
ClassWidgets/SDK/__init__.py
ClassWidgets/SDK/__init__.pyi
ClassWidgets/SDK/api.pyi
ClassWidgets/SDK/config.pyi
ClassWidgets/SDK/notification.pyi
ClassWidgets/SDK/plugin_base.pyi
ClassWidgets/SDK/py.typed
ClassWidgets/SDK/assets/default_icon.png
ClassWidgets/SDK/tools/__init__.py
ClassWidgets/SDK/tools/help.py
ClassWidgets/SDK/tools/manifest.py
ClassWidgets/SDK/tools/packager.py
ClassWidgets/SDK/tools/scaffold.py
class_widgets_sdk-0.3.2.dist-info/METADATA
class_widgets_sdk-0.3.2.dist-info/WHEEL
class_widgets_sdk-0.3.2.dist-info/entry_points.txt
class_widgets_sdk-0.3.2.dist-info/licenses/LICENSE
class_widgets_sdk-0.3.2.dist-info/RECORD
