Metadata-Version: 2.4
Name: Class-Widgets-SDK
Version: 0.3.2
Summary: Class Widgets 2 Plugin SDK Development tools and type stubs
License-File: LICENSE
Requires-Python: >=3.9
Requires-Dist: click
Requires-Dist: pydantic
Provides-Extra: test
Requires-Dist: pyside6; extra == 'test'
Requires-Dist: rinui; extra == 'test'
